cdklabs/cdk_amazonmq/__init__.py
cdklabs/cdk_amazonmq/py.typed
cdklabs/cdk_amazonmq/_jsii/__init__.py
cdklabs/cdk_amazonmq/_jsii/cdk-amazonmq@0.1.8.jsii.tgz
cdklabs_cdk_amazonmq-0.1.8.dist-info/LICENSE
cdklabs_cdk_amazonmq-0.1.8.dist-info/METADATA
cdklabs_cdk_amazonmq-0.1.8.dist-info/WHEEL
cdklabs_cdk_amazonmq-0.1.8.dist-info/top_level.txt
cdklabs_cdk_amazonmq-0.1.8.dist-info/RECORD
